gitask/__init__.py
gitask/commands.py
gitask/main.py
gitask/utils.py
gitask/config/__init__.py
gitask/config/config.py
gitask/config/config_utils.py
gitask/pmt/__init__.py
gitask/pmt/github_pmt.py
gitask/pmt/jira_pmt.py
gitask/pmt/pmt_factory.py
gitask/pmt/project_management_tool.py
gitask/vcs/__init__.py
gitask/vcs/github_vcs.py
gitask/vcs/gitlab_vcs.py
gitask/vcs/vcs_factory.py
gitask/vcs/version_control_tool.py
gitask-1.2.0.dist-info/licenses/LICENSE
gitask-1.2.0.dist-info/METADATA
gitask-1.2.0.dist-info/WHEEL
gitask-1.2.0.dist-info/entry_points.txt
gitask-1.2.0.dist-info/top_level.txt
gitask-1.2.0.dist-info/RECORD
