Metadata-Version: 2.4
Name: gitask
Version: 1.2.0
Summary: A CLI tool to streamline your workflow by integrating with your PMT and VCS.
Home-page: https://github.com/shahafMordechay/Gitask
Author: Shahaf Mordechay
License: MIT License
Project-URL: homepage, https://github.com/shahafMordechay/Gitask
Project-URL: repository, https://github.com/shahafMordechay/Gitask
Classifier: Programming Language :: Python :: 3
Classifier: License :: OSI Approved :: MIT License
Classifier: Operating System :: OS Independent
Requires-Python: >=3.6
License-File: LICENSE
Requires-Dist: click
Requires-Dist: jira
Requires-Dist: requests
Requires-Dist: python-gitlab>=5.6.0
Requires-Dist: PyGithub>=2.1.1
Requires-Dist: pyjwt[crypto]>=2.4.0
Dynamic: home-page
Dynamic: license-file
Dynamic: requires-python
